{
  "format_version": 1,
  "indexes": {
    "awesome": {
      "format_version": 1,
      "index_version": "0.4.63",
      "index_name": "awesome",
      "generated_at": "2026-07-12T04:40:24Z",
      "source_commit": "c17ca547a16ce02f129215256ffc69a031d32f0b",
      "artifact": {
        "name": "xim-index-awesome-0.4.63.tar.gz",
        "sha256": "4df50144454d18cb9808e343171db0f242cf3fa8654e5be47c6fd95a694789ad",
        "size": 7551
      },
      "signature": null
    },
    "d2x": {
      "format_version": 1,
      "index_version": "0.4.63",
      "index_name": "d2x",
      "generated_at": "2026-07-12T04:40:25Z",
      "source_commit": "5f2a4c19d10b399d0a4aa455cc0d4557874bea4f",
      "artifact": {
        "name": "xim-index-d2x-0.4.63.tar.gz",
        "sha256": "965572fb73026a58f57df61f91c166f36d5c969673922f42998788e1db8133a0",
        "size": 6255
      },
      "signature": null
    },
    "xim": {
      "format_version": 1,
      "index_version": "cc4e8c7",
      "index_name": "xim",
      "generated_at": "2026-07-12T07:52:35Z",
      "source_commit": "cc4e8c7f3806ee84751259accfadd4858bad44e4",
      "artifact": {
        "name": "xim-index-cc4e8c7.tar.gz",
        "sha256": "fa64e4f9d52f7be9d72b1d173eaaf2aafaa6fbe7df8951c251ebf064780e8de9",
        "size": 274033
      },
      "signature": null
    },
    "scode": {
      "format_version": 1,
      "index_version": "0.4.63",
      "index_name": "scode",
      "generated_at": "2026-07-12T04:40:24Z",
      "source_commit": "9ac17094697943ccc356e65ff59ac7404fe1a148",
      "artifact": {
        "name": "xim-index-scode-0.4.63.tar.gz",
        "sha256": "f153764d8b3b32444ce44d838cc966b9a06519b7d7a156746ba40ca8d4a0bc6a",
        "size": 8203
      },
      "signature": null
    }
  }
}